[{"content":"Cepeda la Mora\n","description":"paisaje gallery","id":0,"section":"gallery","tags":null,"title":"Paisaje","uri":"https://hotspotcepeda.github.io/es/gallery/paisaje/"},{"content":"BBDD\n1 2 3 4 5 6  docker run -d \\ -v `pwd`/mysql:/var/lib/mysql \\ -v `pwd`/50-server.cnf:/etc/mysql/mariadb.conf.d/50-server.cnf:ro \\ -e MYSQL_ROOT_PASSWORD=mysqlPASWORD \\ –name librenms-db \\ mariadb:latest   Lanza librenms, se asocia a la BBDD\n1 2 3 4 5 6 7 8 9 10 11 12 13  docker run -d \\ -v `pwd`/data:/data \\ -p 888:80 \\ -e TZ=»Europe/Madrid» \\ –link 0bd3a3993581(id container BBDD):mysql \\ -e POLLER=24 \\ -e DB_TYPE=mysql \\ -e DB_HOST=mysql \\ -e DB_NAME=librenms \\ -e DB_USER=root \\ -e DB_PASS=mysqlPASWORD \\ –name librenms \\ seti/librenms   Al navegador http://ipserver:888/install.php\n","description":"Instalar LibreNMS en un contenedor de Docker","id":1,"section":"posts","tags":["docker","librenms","debian"],"title":"Librenms Docker install","uri":"https://hotspotcepeda.github.io/es/posts/librenms_docker_install/"},{"content":"ADD NEXTCLOUD REPOSITORY\nAdd the Nextcloud repository in the /etc/apt/sources.d/nextcloud.list\n1  echo \u0026#39;deb http://apt.jurisic.org/debian/ jessie main contrib non-free\u0026#39; \u0026gt;\u0026gt; /etc/apt/sources.list.d/nextcloud.list   Install release key of Nextcloud repository:\n1  wget -q http://apt.jurisic.org/Release.key -O- | apt-key add -   And run apt-get update to download the list of packages.\n1  apt-get update   INSTALL NEXTCLOUD CLIENT\nInstall Nextcloud server with:\n1  apt-get install nextcloud-client   INSTALL NEXTCLOUD SERVER\nINSTALL POSTGRESQL AND SETUP NEW USER \u0026amp; DATABASE\nInstall PostgreSQL with:\n1  apt-get install postgresql    The PostgreSQL package will install all required dependencies. Choose «y» to start the installation. Add a PostgreSQL database The next step is to create a PostgreSQL database for nextcloud. Login to PostgreSQL on the commandline by running this command:  1 2  su - postgres psql   Enter the following commands to create a database user with the name «nextuser» and and a database name «nextcloud». Replace the word «StorngPasswordHere» with your own password in the commands.\n1 2 3  CREATE DATABASE nextcloud; CREATE USER nextuser WITH PASSWORD \u0026#39;StorngPasswordHere\u0026#39;; GRANT ALL PRIVILEGES ON DATABASE nextcloud to nextuser;   Install Nextcloud server with:\n1  apt-get install nextcloud-server   When the shell part of the installation is finished, proceed by opening the Nextcloud web installer in your browser. The URL is http://[YOURIP]/nextcloud. In my case the IP is 192.168.1.100 so I enter http://192.168.1.100/nextcloud in my browser to get the installer:\nEnter the desired administrator username and password in the login fields. Please choose a secure password and also a username that is not «admin» or «administrator» might be a good choice to make it less easy for attackers to guess your admin login.\nNextcloud is using sqlite as storage engine by default. This is not a good choice performace wise, so I will choose PostgreSQL as database backend. We have created a PostgreSQL database above, enter the details of that database now:\nUsername: nextuser\nPassword: The password that you have choosen for the database.\nDatabase name: nextcloud\nHostname: localhost\nACCESS NEXTCLOUD WITH SSL (HTTPS)\nThe default installation of Nextcloud is not secured by SSL. To enable SSL in your webserver, run these commands:\n1 2 3  a2enmod ssl a2ensite default-ssl service apache2 restart   Now you can access the web interface with https://[YOURIP]/nextcloud. You will probably get a SSL warning, this warning should be accepted. To avoid such warnings, get a free officially signed SSL certificate e.g. from Startssl (or check LetsEncrypt).\nLETSENCRYPT\nSTEP 1 — DOWNLOAD THE LET’S ENCRYPT CLIENT\nThe first step to using Let’s Encrypt to obtain an SSL certificate is to install the certbot software on your server. The Certbot developers maintain their own Ubuntu software repository with up-to-date versions of the software. Because Certbot is in such active development it’s worth using this repository to install a newer Certbot than provided by Ubuntu.\nFirst, add the repository:\n1  sudo add-apt-repository ppa:certbot/certbot   You’ll need to press ENTER to accept. Afterwards, update the package list to pick up the new repository’s package information:\n1  sudo apt-get update   And finally, install Certbot from the new repository with apt-get:\n1  sudo apt-get install python-certbot-apache   The certbot Let’s Encrypt client is now ready to use.\nSTEP 2 — SET UP THE SSL CERTIFICATE\n1  letsencrypt --apache   ","description":"NEXTCLOUD DEBIAN SERVER AND CLIENT","id":2,"section":"posts","tags":["docker","nextcloud","debian"],"title":"NEXTCLOUD DEBIAN SERVER AND CLIENT","uri":"https://hotspotcepeda.github.io/es/posts/nextcloud_debian_debian_server_and_client/"},{"content":"El proposito de este sitio es:\n Compartir la experiencia del proyecto de red comunitaria en Cepeda. Archivar y mantener disponible la documentación técnica. Dar las graciaspor la ayuda recibida e intentar ayudar al que lo necesite para replicar este proyecto de red comunitaria en otros lugares.  Si desea colaborar en el proyecto de Cepeda, en este sitio para aportar contenido, como redactor, traductor o simplemente para expresar su opinión, le invito a contactar mediante el canal de matrix creado para esto y contribuir en github.\nPienso que las telecomunicaciones en nuestra sociedad actual tienen que estar al alcance de todas las personas y por ello las considero un derecho fundamental, como lo son la educación o la sanidad pública. Quiero agradecer a todas esas personas que comparten su experiencia, conocimientos e información para ponerlas al servicio del desarrollo de la humanidad de manera desinteresada.\nTambién quiero añadir que no soy programador profesional y que no hago esto con fines lucrativos, solo hago esto porque me gustan las telecomunicaciones y la tecnología. Si de alguna manera me equivoco acepte mis más sinceras disculpas y no dude en corregirme.\r ","description":"descripcion del sitio","id":3,"section":"","tags":null,"title":"Sitio","uri":"https://hotspotcepeda.github.io/es/sitio/"},{"content":"Fotos de la Red\n","description":"Galeria fotos de Red","id":4,"section":"gallery","tags":null,"title":"Red","uri":"https://hotspotcepeda.github.io/es/gallery/red/"}]